draftjs_exporter/__init__.py
draftjs_exporter/command.py
draftjs_exporter/composite_decorators.py
draftjs_exporter/constants.py
draftjs_exporter/defaults.py
draftjs_exporter/dom.py
draftjs_exporter/entity_state.py
draftjs_exporter/error.py
draftjs_exporter/html.py
draftjs_exporter/options.py
draftjs_exporter/py.typed
draftjs_exporter/style_state.py
draftjs_exporter/types.py
draftjs_exporter/wrapper_state.py
draftjs_exporter/engines/__init__.py
draftjs_exporter/engines/base.py
draftjs_exporter/engines/html5lib.py
draftjs_exporter/engines/lxml.py
draftjs_exporter/engines/string.py
draftjs_exporter/engines/string_compat.py
draftjs_exporter/utils/__init__.py
draftjs_exporter/utils/module_loading.py
draftjs_exporter-5.0.0.dist-info/LICENSE
draftjs_exporter-5.0.0.dist-info/METADATA
draftjs_exporter-5.0.0.dist-info/WHEEL
draftjs_exporter-5.0.0.dist-info/top_level.txt
draftjs_exporter-5.0.0.dist-info/RECORD
